setup.py
ComponentPermissionsPlugin.egg-info/PKG-INFO
ComponentPermissionsPlugin.egg-info/SOURCES.txt
ComponentPermissionsPlugin.egg-info/dependency_links.txt
ComponentPermissionsPlugin.egg-info/entry_points.txt
ComponentPermissionsPlugin.egg-info/not-zip-safe
ComponentPermissionsPlugin.egg-info/top_level.txt
componentpermissions/__init__.py
componentpermissions/api.py