Metadata-Version: 1.0
Name: ComponentPermissionsPlugin
Version: 0.1.5
Summary: Provides permissions based on ticket components for Trac.
Home-page: http://mitar.tnode.com/
Author: Mitar
Author-email: mitar.trac@tnode.com
License: AGPLv3
Keywords: trac plugin
Platform: UNKNOWN
